Metadata-Version: 2.4
Name: mseep-mcp-tenki
Version: 0.1.1
Summary: Get weather of Japan
Author-email: mseep <support@skydeck.ai>
Requires-Python: >=3.12
License-File: LICENSE
Requires-Dist: httpx>=0.28.1
Requires-Dist: mcp[cli]>=1.2.0
Requires-Dist: pydantic>=2.10.5
Dynamic: license-file
